[
  {
    "repo": "uisikdag/yolo-v8-football-players-detection",
    "file": "best.pt",
    "local_path": "models\\football_hf\\uisikdag__yolo-v8-football-players-detection__best.pt",
    "url": "https://huggingface.co/uisikdag/yolo-v8-football-players-detection/resolve/main/best.pt",
    "size": 22494328,
    "load_status": "ok",
    "model_type": "YOLO",
    "names": {
      "0": "ball",
      "1": "goalkeeper",
      "2": "player",
      "3": "referee"
    }
  },
  {
    "repo": "tmoklc/football-player-detection",
    "file": "football-player-detection.pt",
    "local_path": "models\\football_hf\\tmoklc__football-player-detection__football-player-detection.pt",
    "url": "https://huggingface.co/tmoklc/football-player-detection/resolve/main/football-player-detection.pt",
    "size": 136802409,
    "load_status": "ok",
    "model_type": "YOLO",
    "names": {
      "0": "ball",
      "1": "goalkeeper",
      "2": "player",
      "3": "referee"
    }
  },
  {
    "repo": "maerie88/FOOTBALL-PLAYER-DETECTION-MODEL",
    "file": "best.pt",
    "local_path": "models\\football_hf\\maerie88__FOOTBALL-PLAYER-DETECTION-MODEL__best.pt",
    "url": "https://huggingface.co/maerie88/FOOTBALL-PLAYER-DETECTION-MODEL/resolve/main/best.pt",
    "size": 5626963,
    "load_status": "ok",
    "model_type": "YOLO",
    "names": {
      "0": "ball",
      "1": "goalkeeper",
      "2": "player",
      "3": "referee"
    }
  },
  {
    "repo": "martinjolif/yolo-football-player-detection",
    "file": "yolo-football-player-detection.pt",
    "local_path": "models\\football_hf\\martinjolif__yolo-football-player-detection__yolo-football-player-detection.pt",
    "url": "https://huggingface.co/martinjolif/yolo-football-player-detection/resolve/main/yolo-football-player-detection.pt",
    "size": 40583084,
    "load_status": "ok",
    "model_type": "YOLO",
    "names": {
      "0": "ball",
      "1": "goalkeeper",
      "2": "player",
      "3": "referee"
    }
  },
  {
    "repo": "HamzaAliKhan/football-players-detection",
    "file": "best_players_detection.pt",
    "local_path": "models\\football_hf\\HamzaAliKhan__football-players-detection__best_players_detection.pt",
    "url": "https://huggingface.co/HamzaAliKhan/football-players-detection/resolve/main/best_players_detection.pt",
    "size": 40525484,
    "load_status": "ok",
    "model_type": "YOLO",
    "names": {
      "0": "ball",
      "1": "goalkeeper",
      "2": "player",
      "3": "referee"
    }
  },
  {
    "repo": "mobadam/football-player-detection",
    "file": "player_detector.pt",
    "local_path": "models\\football_hf\\mobadam__football-player-detection__player_detector.pt",
    "url": "https://huggingface.co/mobadam/football-player-detection/resolve/main/player_detector.pt",
    "size": 53140901,
    "load_status": "ok",
    "model_type": "YOLO",
    "names": {
      "0": "ball",
      "1": "player",
      "2": "referee",
      "3": "goalkeeper"
    }
  },
  {
    "repo": "asahwells/yolo26n-football-detection",
    "file": "weights/best.pt",
    "local_path": "models\\football_hf\\asahwells__yolo26n-football-detection__weights__best.pt",
    "url": "https://huggingface.co/asahwells/yolo26n-football-detection/resolve/main/weights/best.pt",
    "size": 5458117,
    "load_status": "ok",
    "model_type": "YOLO",
    "names": {
      "0": "ball",
      "1": "goalkeeper",
      "2": "player",
      "3": "referee"
    }
  },
  {
    "repo": "jhsu12/yolov8n-football-finetuned",
    "file": "weights/best.pt",
    "local_path": "models\\football_hf\\jhsu12__yolov8n-football-finetuned__weights__best.pt",
    "url": "https://huggingface.co/jhsu12/yolov8n-football-finetuned/resolve/main/weights/best.pt",
    "size": 136885171,
    "load_status": "ok",
    "model_type": "YOLO",
    "names": {
      "0": "ball",
      "1": "goalkeeper",
      "2": "player",
      "3": "referee"
    }
  },
  {
    "repo": "hoseinshr1055/yolov8-football-detection",
    "file": "yolov8_football.pt",
    "local_path": "models\\football_hf\\hoseinshr1055__yolov8-football-detection__yolov8_football.pt",
    "url": "https://huggingface.co/hoseinshr1055/yolov8-football-detection/resolve/main/yolov8_football.pt",
    "size": 6549796,
    "load_status": "ok",
    "model_type": "YOLO",
    "names": {
      "0": "person",
      "1": "bicycle",
      "2": "car",
      "3": "motorcycle",
      "4": "airplane",
      "5": "bus",
      "6": "train",
      "7": "truck",
      "8": "boat",
      "9": "traffic light",
      "10": "fire hydrant",
      "11": "stop sign",
      "12": "parking meter",
      "13": "bench",
      "14": "bird",
      "15": "cat",
      "16": "dog",
      "17": "horse",
      "18": "sheep",
      "19": "cow",
      "20": "elephant",
      "21": "bear",
      "22": "zebra",
      "23": "giraffe",
      "24": "backpack",
      "25": "umbrella",
      "26": "handbag",
      "27": "tie",
      "28": "suitcase",
      "29": "frisbee",
      "30": "skis",
      "31": "snowboard",
      "32": "sports ball",
      "33": "kite",
      "34": "baseball bat",
      "35": "baseball glove",
      "36": "skateboard",
      "37": "surfboard",
      "38": "tennis racket",
      "39": "bottle",
      "40": "wine glass",
      "41": "cup",
      "42": "fork",
      "43": "knife",
      "44": "spoon",
      "45": "bowl",
      "46": "banana",
      "47": "apple",
      "48": "sandwich",
      "49": "orange",
      "50": "broccoli",
      "51": "carrot",
      "52": "hot dog",
      "53": "pizza",
      "54": "donut",
      "55": "cake",
      "56": "chair",
      "57": "couch",
      "58": "potted plant",
      "59": "bed",
      "60": "dining table",
      "61": "toilet",
      "62": "tv",
      "63": "laptop",
      "64": "mouse",
      "65": "remote",
      "66": "keyboard",
      "67": "cell phone",
      "68": "microwave",
      "69": "oven",
      "70": "toaster",
      "71": "sink",
      "72": "refrigerator",
      "73": "book",
      "74": "clock",
      "75": "vase",
      "76": "scissors",
      "77": "teddy bear",
      "78": "hair drier",
      "79": "toothbrush"
    }
  },
  {
    "repo": "hoseinshr1055/yolov8-football-detection",
    "file": "yolov8m_football_best_4.pt",
    "local_path": "models\\football_hf\\hoseinshr1055__yolov8-football-detection__yolov8m_football_best_4.pt",
    "url": "https://huggingface.co/hoseinshr1055/yolov8-football-detection/resolve/main/yolov8m_football_best_4.pt",
    "size": 52086283,
    "load_status": "ok",
    "model_type": "YOLO",
    "names": {
      "0": "player"
    }
  },
  {
    "repo": "ParsaGh/yolov8_football",
    "file": "best.pt",
    "local_path": "models\\football_hf\\ParsaGh__yolov8_football__best.pt",
    "url": "https://huggingface.co/ParsaGh/yolov8_football/resolve/main/best.pt",
    "size": 6310243,
    "load_status": "ok",
    "model_type": "YOLO",
    "names": {
      "0": "ball",
      "1": "player",
      "2": "referee",
      "3": "other"
    }
  },
  {
    "repo": "martinjolif/yolo-football-ball-detection",
    "file": "yolo-football-ball-detection.pt",
    "local_path": "models\\football_hf\\martinjolif__yolo-football-ball-detection__yolo-football-ball-detection.pt",
    "url": "https://huggingface.co/martinjolif/yolo-football-ball-detection/resolve/main/yolo-football-ball-detection.pt",
    "size": 5535706,
    "load_status": "ok",
    "model_type": "YOLO",
    "names": {
      "0": "ball"
    }
  },
  {
    "repo": "ShahzainHaider/football_detection",
    "file": "ball_detector.pt",
    "local_path": "models\\football_hf\\ShahzainHaider__football_detection__ball_detector.pt",
    "url": "https://huggingface.co/ShahzainHaider/football_detection/resolve/main/ball_detector.pt",
    "size": 19172122,
    "load_status": "ok",
    "model_type": "YOLO",
    "names": {
      "0": "dog",
      "1": "soccerball"
    }
  },
  {
    "repo": "RajatDave/soccer-ball-detection",
    "file": "soccer_ball.pt",
    "local_path": "models\\football_hf\\RajatDave__soccer-ball-detection__soccer_ball.pt",
    "url": "https://huggingface.co/RajatDave/soccer-ball-detection/resolve/main/soccer_ball.pt",
    "size": 6392974,
    "load_status": "ok",
    "model_type": "YOLO",
    "names": {
      "0": "ball"
    }
  },
  {
    "repo": "RaghavRaahul/soccer_ball_detection",
    "file": "checkpoint_5.pt",
    "local_path": "models\\football_hf\\RaghavRaahul__soccer_ball_detection__checkpoint_5.pt",
    "url": "https://huggingface.co/RaghavRaahul/soccer_ball_detection/resolve/main/checkpoint_5.pt",
    "size": 103119507,
    "load_status": "ok",
    "model_type": "YOLO",
    "names": {
      "0": "person",
      "1": "bicycle",
      "2": "car",
      "3": "motorcycle",
      "4": "airplane",
      "5": "bus",
      "6": "train",
      "7": "truck",
      "8": "boat",
      "9": "traffic light",
      "10": "fire hydrant",
      "11": "stop sign",
      "12": "parking meter",
      "13": "bench",
      "14": "bird",
      "15": "cat",
      "16": "dog",
      "17": "horse",
      "18": "sheep",
      "19": "cow",
      "20": "elephant",
      "21": "bear",
      "22": "zebra",
      "23": "giraffe",
      "24": "backpack",
      "25": "umbrella",
      "26": "handbag",
      "27": "tie",
      "28": "suitcase",
      "29": "frisbee",
      "30": "skis",
      "31": "snowboard",
      "32": "sports ball",
      "33": "kite",
      "34": "baseball bat",
      "35": "baseball glove",
      "36": "skateboard",
      "37": "surfboard",
      "38": "tennis racket",
      "39": "bottle",
      "40": "wine glass",
      "41": "cup",
      "42": "fork",
      "43": "knife",
      "44": "spoon",
      "45": "bowl",
      "46": "banana",
      "47": "apple",
      "48": "sandwich",
      "49": "orange",
      "50": "broccoli",
      "51": "carrot",
      "52": "hot dog",
      "53": "pizza",
      "54": "donut",
      "55": "cake",
      "56": "chair",
      "57": "couch",
      "58": "potted plant",
      "59": "bed",
      "60": "dining table",
      "61": "toilet",
      "62": "tv",
      "63": "laptop",
      "64": "mouse",
      "65": "remote",
      "66": "keyboard",
      "67": "cell phone",
      "68": "microwave",
      "69": "oven",
      "70": "toaster",
      "71": "sink",
      "72": "refrigerator",
      "73": "book",
      "74": "clock",
      "75": "vase",
      "76": "scissors",
      "77": "teddy bear",
      "78": "hair drier",
      "79": "toothbrush"
    }
  }
]